nodeconductor_saltstack/__init__.py
nodeconductor_saltstack/exchange/__init__.py
nodeconductor_saltstack/exchange/admin.py
nodeconductor_saltstack/exchange/apps.py
nodeconductor_saltstack/exchange/backend.py
nodeconductor_saltstack/exchange/cost_tracking.py
nodeconductor_saltstack/exchange/extension.py
nodeconductor_saltstack/exchange/filters.py
nodeconductor_saltstack/exchange/log.py
nodeconductor_saltstack/exchange/models.py
nodeconductor_saltstack/exchange/perms.py
nodeconductor_saltstack/exchange/serializers.py
nodeconductor_saltstack/exchange/tasks.py
nodeconductor_saltstack/exchange/urls.py
nodeconductor_saltstack/exchange/validators.py
nodeconductor_saltstack/exchange/views.py
nodeconductor_saltstack/exchange/migrations/0001_initial.py
nodeconductor_saltstack/exchange/migrations/0002_tenant_tags.py
nodeconductor_saltstack/exchange/migrations/0003_rename_tenant_model.py
nodeconductor_saltstack/exchange/migrations/0004_init_quotas.py
nodeconductor_saltstack/exchange/migrations/0005_contact_group_user.py
nodeconductor_saltstack/exchange/migrations/0006_group_manager_foreign_key.py
nodeconductor_saltstack/exchange/migrations/0007_user_additional_fields.py
nodeconductor_saltstack/exchange/migrations/0008_user_unique_together_fields.py
nodeconductor_saltstack/exchange/migrations/0009_user_username_validation.py
nodeconductor_saltstack/exchange/migrations/0010_group_members.py
nodeconductor_saltstack/exchange/migrations/0011_conferenceroom.py
nodeconductor_saltstack/exchange/migrations/0012_more_members_models.py
nodeconductor_saltstack/exchange/migrations/0013_remove_group_delivery_members.py
nodeconductor_saltstack/exchange/migrations/0014_group_delivery_members.py
nodeconductor_saltstack/exchange/migrations/0015_remove_mailbox_size_max_users.py
nodeconductor_saltstack/exchange/migrations/0016_remove_mailbox_size.py
nodeconductor_saltstack/exchange/migrations/0017_exchangetenant_publishing_state.py
nodeconductor_saltstack-0.5.0.dist-info/DESCRIPTION.rst
nodeconductor_saltstack-0.5.0.dist-info/METADATA
nodeconductor_saltstack-0.5.0.dist-info/RECORD
nodeconductor_saltstack-0.5.0.dist-info/WHEEL
nodeconductor_saltstack-0.5.0.dist-info/entry_points.txt
nodeconductor_saltstack-0.5.0.dist-info/metadata.json
nodeconductor_saltstack-0.5.0.dist-info/top_level.txt
