Metadata-Version: 2.0
Name: nodeconductor-saltstack
Version: 0.5.0
Summary: NodeConductor SaltStack plugin allows to manage applications via SaltStack RPC
Home-page: http://nodeconductor.com
Author: OpenNode Team
Author-email: info@opennodecloud.com
License: UNKNOWN
Platform: UNKNOWN
Classifier: Framework :: Django
Classifier: Intended Audience :: Developers
Classifier: Intended Audience :: System Administrators
Classifier: Operating System :: OS Independent
Classifier: License :: OSI Approved :: MIT License
Requires-Dist: nodeconductor (>0.108.0)
Provides-Extra: dev
Requires-Dist: Sphinx (==1.2.2); extra == 'dev'
